app/App.py
app/__init__.py
hj12hj_app-1.0.0.dist-info/METADATA
hj12hj_app-1.0.0.dist-info/WHEEL
hj12hj_app-1.0.0.dist-info/top_level.txt
hj12hj_app-1.0.0.dist-info/RECORD
